infrastructure/__init__.py
infrastructure/models/__init__.py
infrastructure/models/user_db.py
xbyteruser-0.1.0.dist-info/METADATA
xbyteruser-0.1.0.dist-info/WHEEL
xbyteruser-0.1.0.dist-info/top_level.txt
xbyteruser-0.1.0.dist-info/RECORD
