Metadata-Version: 2.4
Name: xbyteruser
Version: 0.1.0
Summary: A Python package for xbyter user management
Home-page: https://github.com/xbyter001/xbyteruser
Author: xbyter
Author-email: xbyter@outlook.com
Classifier: Programming Language :: Python :: 3
Classifier: License :: OSI Approved :: MIT License
Classifier: Operating System :: OS Independent
Requires-Python: >=3.6
Requires-Dist: pydantic
Requires-Dist: tortoise-orm
Dynamic: author
Dynamic: author-email
Dynamic: classifier
Dynamic: description
Dynamic: description-content-type
Dynamic: home-page
Dynamic: requires-dist
Dynamic: requires-python
Dynamic: summary
